graphene_gae/__init__.py
graphene_gae/ndb/__init__.py
graphene_gae/ndb/converter.py
graphene_gae/ndb/fields.py
graphene_gae/ndb/options.py
graphene_gae/ndb/types.py
graphene_gae/webapp2/__init__.py
graphene_gae-1.0.7.dist-info/DESCRIPTION.rst
graphene_gae-1.0.7.dist-info/METADATA
graphene_gae-1.0.7.dist-info/RECORD
graphene_gae-1.0.7.dist-info/WHEEL
graphene_gae-1.0.7.dist-info/metadata.json
graphene_gae-1.0.7.dist-info/top_level.txt
