Metadata-Version: 1.1
Name: graphene_gae
Version: 1.0.7
Summary: Graphene GAE Integration
Home-page: https://github.com/graphql-python/graphene-gae
Author: Eran Kampf
Author-email: eran@ekampf.com
License: BSD
Keywords: graphene_gae
Platform: UNKNOWN
Classifier: Development Status :: 4 - Beta
Classifier: Intended Audience :: Developers
Classifier: License :: OSI Approved :: BSD License
Classifier: Natural Language :: English
Classifier: Programming Language :: Python :: 2
Classifier: Programming Language :: Python :: 2.7
Classifier: Programming Language :: Python :: 3
Classifier: Programming Language :: Python :: 3.4
